{
  "schema_version": "1.0",
  "scope": "dataset",
  "scene_key": "house-21",
  "scene_file": "house-21-elevation-rechte-giebel.jpg",
  "scene_tag": "ansicht",
  "image_size_px": [
    926,
    936
  ],
  "labels": [
    {
      "id": "71c2e7d0-c4ef-4c4f-9a2a-8ebee4e5dd9a",
      "type": "component_line",
      "geometry": {
        "polyline": [
          [
            305.37890625,
            452.51739501953125
          ],
          [
            526.9667358398438,
            149.11923217773438
          ],
          [
            781.8348999023438,
            450.96807861328125
          ],
          [
            778.0692138671875,
            640.0696411132812
          ],
          [
            326.0988464355469,
            703.154052734375
          ],
          [
            307.1188049316406,
            454.56787109375
          ]
        ]
      },
      "attributes": {
        "line_kind": "dachschraege"
      },
      "status": "readable",
      "relations": [],
      "created_at": "2026-05-27T18:17:49.253Z",
      "updated_at": "2026-05-27T18:17:49.253Z"
    }
  ],
  "annotated_by": "jhoetter",
  "annotated_at": "2026-05-27T18:18:19.265Z"
}